README.txt
setup.cfg
setup.py
collective/__init__.py
collective.portlet.amazon.egg-info/PKG-INFO
collective.portlet.amazon.egg-info/SOURCES.txt
collective.portlet.amazon.egg-info/dependency_links.txt
collective.portlet.amazon.egg-info/entry_points.txt
collective.portlet.amazon.egg-info/namespace_packages.txt
collective.portlet.amazon.egg-info/not-zip-safe
collective.portlet.amazon.egg-info/requires.txt
collective.portlet.amazon.egg-info/top_level.txt
collective/portlet/__init__.py
collective/portlet/amazon/__init__.py
collective/portlet/amazon/amazonportlet.pt
collective/portlet/amazon/amazonportlet.py
collective/portlet/amazon/configure.zcml
collective/portlet/amazon/version.txt
collective/portlet/amazon/profiles/default/portlets.xml
collective/portlet/amazon/tests/__init__.py
collective/portlet/amazon/tests/base.py
collective/portlet/amazon/tests/test_portlet.py
docs/HISTORY.txt
docs/INSTALL.txt
docs/LICENSE.GPL
docs/LICENSE.txt
