Metadata-Version: 1.0
Name: collective.portlet.amazon
Version: 0.2dev-r58081
Summary: This ifor Plone 3 that allows you to display a product from Amazon.com and make money through your Amazon Affiliates account.
Home-page: http://www.speedbreeze.com
Author: Jonathan Wilde
Author-email: plone-developers@lists.sourceforge.net
License: GPL
Keywords: web zope plone portlet amazon
Platform: UNKNOWN
Classifier: Framework :: Plone
Classifier: Framework :: Zope2
Classifier: Framework :: Zope3
Classifier: Programming Language :: Python
Classifier: Topic :: Software Development :: Libraries :: Python Modules
